bap_elk_backends/__init__.py
bap_elk_backends/_version.py
bap_elk_backends/enriched/__init__.py
bap_elk_backends/enriched/pontoon.py
bap_elk_backends/enriched/public_inbox.py
bap_elk_backends/enriched/topicbox.py
bap_elk_backends/raw/__init__.py
bap_elk_backends/raw/pontoon.py
bap_elk_backends/raw/public_inbox.py
bap_elk_backends/raw/topicbox.py
bap_elk_backends/utils.py
bap_elk_backends-0.8.4.dist-info/METADATA
bap_elk_backends-0.8.4.dist-info/WHEEL
bap_elk_backends-0.8.4.dist-info/entry_points.txt
bap_elk_backends-0.8.4.dist-info/licenses/AUTHORS
bap_elk_backends-0.8.4.dist-info/licenses/LICENSE
bap_elk_backends-0.8.4.dist-info/RECORD
