Metadata-Version: 2.4
Name: bap-elk-backends
Version: 0.8.4
Summary: GrimoireELK plugic for public-inbox.
License: GPL-3.0+
License-File: AUTHORS
License-File: LICENSE
Keywords: development,grimoirelab
Author: Bitergia Developers
Requires-Python: >=3.10,<4.0
Classifier: Development Status :: 4 - Beta
Classifier: Intended Audience :: Developers
Classifier: Intended Audience :: Science/Research
Classifier: License :: OSI Approved :: GNU General Public License v3 or later (GPLv3+)
Classifier: Programming Language :: Python :: 3
Classifier: Programming Language :: Python :: 3.10
Classifier: Programming Language :: Python :: 3.11
Classifier: Programming Language :: Python :: 3.12
Classifier: Programming Language :: Python :: 3.13
Classifier: Programming Language :: Python :: 3.14
Classifier: Topic :: Software Development
Requires-Dist: grimoire-elk (>=0.106.0)
Requires-Dist: perceval-pontoon (>=0.1.0rc2)
Requires-Dist: perceval-public-inbox (>=0.1.1)
Requires-Dist: perceval-topicbox (>=0.1.0rc2)
Project-URL: Bug Tracker, https://github.com/bitergia-analytics/bitergia-analytics-elk-backends/issues
Project-URL: Homepage, https://chaoss.github.io/grimoirelab/
Project-URL: Repository, https://github.com/bitergia-analytics/bitergia-analytics-elk-backends
